nbpickup/__init__.py
nbpickup/authoring.py
nbpickup/gradebook_tools.py
nbpickup/grading.py
nbpickup/submissions.py
nbpickup/EventHandlers/__init__.py
nbpickup/EventHandlers/autosave_authoring.py
nbpickup/EventHandlers/autosave_gradebook.py
nbpickup/Helpers/__init__.py
nbpickup/Helpers/jupyter_tools.py
nbpickup-0.9.3.dist-info/LICENSE
nbpickup-0.9.3.dist-info/METADATA
nbpickup-0.9.3.dist-info/WHEEL
nbpickup-0.9.3.dist-info/top_level.txt
nbpickup-0.9.3.dist-info/RECORD
