Metadata-Version: 2.1
Name: nbpickup
Version: 0.9.3
Summary: Library for collecting and distribution of coding assessments using nbgrader and Binder.
Home-page: https://github.com/jjur/nbpickup-client-python
Author: Juraj Vasek
Author-email: juraj.vasek@uni.minerva.edu
License: MIT
Platform: UNKNOWN
Classifier: Programming Language :: Python :: 3
Classifier: License :: OSI Approved :: MIT License
Classifier: Operating System :: OS Independent
Requires-Python: >=3
Requires-Dist: requests
Requires-Dist: ipykernel
Requires-Dist: ipython
Requires-Dist: watchdog
Requires-Dist: nbgrader
